click_tracker/__init__.py
click_tracker/tracker.py
click_tracker/utils.py
click_tracker-0.1.0.dist-info/METADATA
click_tracker-0.1.0.dist-info/WHEEL
click_tracker-0.1.0.dist-info/top_level.txt
click_tracker-0.1.0.dist-info/RECORD
